odoo/addons/hr_recruitment_torecruit/README.rst
odoo/addons/hr_recruitment_torecruit/__init__.py
odoo/addons/hr_recruitment_torecruit/__manifest__.py
odoo/addons/hr_recruitment_torecruit/i18n/es.po
odoo/addons/hr_recruitment_torecruit/i18n/hr_recruitment_torecruit.pot
odoo/addons/hr_recruitment_torecruit/i18n/it.po
odoo/addons/hr_recruitment_torecruit/models/__init__.py
odoo/addons/hr_recruitment_torecruit/models/hr_contract.py
odoo/addons/hr_recruitment_torecruit/models/hr_job.py
odoo/addons/hr_recruitment_torecruit/readme/CONTRIBUTORS.rst
odoo/addons/hr_recruitment_torecruit/readme/DESCRIPTION.rst
odoo/addons/hr_recruitment_torecruit/readme/USAGE.rst
odoo/addons/hr_recruitment_torecruit/static/description/icon.png
odoo/addons/hr_recruitment_torecruit/static/description/index.html
odoo/addons/hr_recruitment_torecruit/tests/__init__.py
odoo/addons/hr_recruitment_torecruit/tests/test_hr_recruitment_torecruit.py
odoo/addons/hr_recruitment_torecruit/views/hr_job.xml
odoo_addon_hr_recruitment_torecruit-16.0.1.1.0.4.dist-info/METADATA
odoo_addon_hr_recruitment_torecruit-16.0.1.1.0.4.dist-info/WHEEL
odoo_addon_hr_recruitment_torecruit-16.0.1.1.0.4.dist-info/top_level.txt
odoo_addon_hr_recruitment_torecruit-16.0.1.1.0.4.dist-info/RECORD
